{"cameraMode":{"drawMode":0,"name":"Shaded","section":"Shading Mode"},"sceneLighting":true,"audioPlay":false,"sceneViewState":{"showFog":true,"showMaterialUpdate":false,"showSkybox":true,"showFlares":true,"showImageEffects":true,"showParticleSystems":true},"in2DMode":false,"pivot":{"x":324.4927062988281,"y":159.56326293945313,"z":129.96636962890626},"rotation":{"x":0.20115377008914948,"y":-0.08948907256126404,"z":0.01845705136656761,"w":0.9752909541130066},"size":368.80682373046877,"orthographic":false}